LICENSE
MANIFEST.in
README.md
scrapy.cfg
setup.cfg
setup.py
lich_scrapy_pod_pipeline/__init__.py
lich_scrapy_pod_pipeline/items.py
lich_scrapy_pod_pipeline/middlewares.py
lich_scrapy_pod_pipeline/pipelines.py
lich_scrapy_pod_pipeline/sender.py
lich_scrapy_pod_pipeline/settings.py
lich_scrapy_pod_pipeline/utils.py
lich_scrapy_pod_pipeline.egg-info/PKG-INFO
lich_scrapy_pod_pipeline.egg-info/SOURCES.txt
lich_scrapy_pod_pipeline.egg-info/dependency_links.txt
lich_scrapy_pod_pipeline.egg-info/not-zip-safe
lich_scrapy_pod_pipeline.egg-info/requires.txt
lich_scrapy_pod_pipeline.egg-info/top_level.txt
lich_scrapy_pod_pipeline/spiders/__init__.py
requirements/requirements-lint.txt
requirements/requirements-test.txt
requirements/requirements.txt
tests/__init__.py
tests/test_scrapy_check.py